MANIFEST.in
README.md
setup.py
ugc_sentiment/__init__.py
ugc_sentiment.egg-info/PKG-INFO
ugc_sentiment.egg-info/SOURCES.txt
ugc_sentiment.egg-info/dependency_links.txt
ugc_sentiment.egg-info/top_level.txt
ugc_sentiment/docs/model/category
ugc_sentiment/docs/model/default_best.h5
ugc_sentiment/docs/model/params
ugc_sentiment/docs/model/vocabulary_inv
ugc_sentiment/scripts/__init__.py
ugc_sentiment/scripts/sentiment_train.py
ugc_sentiment/scripts/tool.py
ugc_sentiment/utils/__init__.py
ugc_sentiment/utils/assemble.py
ugc_sentiment/utils/config.yaml
ugc_sentiment/utils/dataHelper.py